{
  "source_pdf": "F:\\材料科学基础_知识库\\00_source\\original.pdf",
  "generated_at": "2026-06-30T20:25:27",
  "total_pages": 699,
  "rendered_range": [
    21,
    100
  ],
  "pages": [
    {
      "page": 21,
      "image": "F:\\材料科学基础_知识库\\01_renders\\page_0021.png",
      "size": {
        "width": 1029,
        "height": 1410
      }
    },
    {
      "page": 22,
      "image": "F:\\材料科学基础_知识库\\01_renders\\page_0022.png",
      "size": {
        "width": 1029,
        "height": 1410
      }
    },
    {
      "page": 23,
      "image": "F:\\材料科学基础_知识库\\01_renders\\page_0023.png",
      "size": {
        "width": 1029,
        "height": 1410
      }
    },
    {
      "page": 24,
      "image": "F:\\材料科学基础_知识库\\01_renders\\page_0024.png",
      "size": {
        "width": 1029,
        "height": 1410
      }
    },
    {
      "page": 25,
      "image": "F:\\材料科学基础_知识库\\01_renders\\page_0025.png",
      "size": {
        "width": 1029,
        "height": 1410
      }
    },
    {
      "page": 26,
      "image": "F:\\材料科学基础_知识库\\01_renders\\page_0026.png",
      "size": {
        "width": 1029,
        "height": 1410
      }
    },
    {
      "page": 27,
      "image": "F:\\材料科学基础_知识库\\01_renders\\page_0027.png",
      "size": {
        "width": 1029,
        "height": 1410
      }
    },
    {
      "page": 28,
      "image": "F:\\材料科学基础_知识库\\01_renders\\page_0028.png",
      "size": {
        "width": 1029,
        "height": 1410
      }
    },
    {
      "page": 29,
      "image": "F:\\材料科学基础_知识库\\01_renders\\page_0029.png",
      "size": {
        "width": 1029,
        "height": 1410
      }
    },
    {
      "page": 30,
      "image": "F:\\材料科学基础_知识库\\01_renders\\page_0030.png",
      "size": {
        "width": 1029,
        "height": 1410
      }
    },
    {
      "page": 31,
      "image": "F:\\材料科学基础_知识库\\01_renders\\page_0031.png",
      "size": {
        "width": 1029,
        "height": 1410
      }
    },
    {
      "page": 32,
      "image": "F:\\材料科学基础_知识库\\01_renders\\page_0032.png",
      "size": {
        "width": 1029,
        "height": 1410
      }
    },
    {
      "page": 33,
      "image": "F:\\材料科学基础_知识库\\01_renders\\page_0033.png",
      "size": {
        "width": 1029,
        "height": 1410
      }
    },
    {
      "page": 34,
      "image": "F:\\材料科学基础_知识库\\01_renders\\page_0034.png",
      "size": {
        "width": 1029,
        "height": 1410
      }
    },
    {
      "page": 35,
      "image": "F:\\材料科学基础_知识库\\01_renders\\page_0035.png",
      "size": {
        "width": 1029,
        "height": 1410
      }
    },
    {
      "page": 36,
      "image": "F:\\材料科学基础_知识库\\01_renders\\page_0036.png",
      "size": {
        "width": 1029,
        "height": 1410
      }
    },
    {
      "page": 37,
      "image": "F:\\材料科学基础_知识库\\01_renders\\page_0037.png",
      "size": {
        "width": 1029,
        "height": 1410
      }
    },
    {
      "page": 38,
      "image": "F:\\材料科学基础_知识库\\01_renders\\page_0038.png",
      "size": {
        "width": 1029,
        "height": 1410
      }
    },
    {
      "page": 39,
      "image": "F:\\材料科学基础_知识库\\01_renders\\page_0039.png",
      "size": {
        "width": 1029,
        "height": 1410
      }
    },
    {
      "page": 40,
      "image": "F:\\材料科学基础_知识库\\01_renders\\page_0040.png",
      "size": {
        "width": 1029,
        "height": 1410
      }
    },
    {
      "page": 41,
      "image": "F:\\材料科学基础_知识库\\01_renders\\page_0041.png",
      "size": {
        "width": 1029,
        "height": 1410
      }
    },
    {
      "page": 42,
      "image": "F:\\材料科学基础_知识库\\01_renders\\page_0042.png",
      "size": {
        "width": 1029,
        "height": 1410
      }
    },
    {
      "page": 43,
      "image": "F:\\材料科学基础_知识库\\01_renders\\page_0043.png",
      "size": {
        "width": 1029,
        "height": 1410
      }
    },
    {
      "page": 44,
      "image": "F:\\材料科学基础_知识库\\01_renders\\page_0044.png",
      "size": {
        "width": 1029,
        "height": 1410
      }
    },
    {
      "page": 45,
      "image": "F:\\材料科学基础_知识库\\01_renders\\page_0045.png",
      "size": {
        "width": 1029,
        "height": 1410
      }
    },
    {
      "page": 46,
      "image": "F:\\材料科学基础_知识库\\01_renders\\page_0046.png",
      "size": {
        "width": 1029,
        "height": 1410
      }
    },
    {
      "page": 47,
      "image": "F:\\材料科学基础_知识库\\01_renders\\page_0047.png",
      "size": {
        "width": 1029,
        "height": 1410
      }
    },
    {
      "page": 48,
      "image": "F:\\材料科学基础_知识库\\01_renders\\page_0048.png",
      "size": {
        "width": 1029,
        "height": 1410
      }
    },
    {
      "page": 49,
      "image": "F:\\材料科学基础_知识库\\01_renders\\page_0049.png",
      "size": {
        "width": 1029,
        "height": 1410
      }
    },
    {
      "page": 50,
      "image": "F:\\材料科学基础_知识库\\01_renders\\page_0050.png",
      "size": {
        "width": 1029,
        "height": 1410
      }
    },
    {
      "page": 51,
      "image": "F:\\材料科学基础_知识库\\01_renders\\page_0051.png",
      "size": {
        "width": 1029,
        "height": 1410
      }
    },
    {
      "page": 52,
      "image": "F:\\材料科学基础_知识库\\01_renders\\page_0052.png",
      "size": {
        "width": 1029,
        "height": 1410
      }
    },
    {
      "page": 53,
      "image": "F:\\材料科学基础_知识库\\01_renders\\page_0053.png",
      "size": {
        "width": 1029,
        "height": 1410
      }
    },
    {
      "page": 54,
      "image": "F:\\材料科学基础_知识库\\01_renders\\page_0054.png",
      "size": {
        "width": 1029,
        "height": 1410
      }
    },
    {
      "page": 55,
      "image": "F:\\材料科学基础_知识库\\01_renders\\page_0055.png",
      "size": {
        "width": 1029,
        "height": 1410
      }
    },
    {
      "page": 56,
      "image": "F:\\材料科学基础_知识库\\01_renders\\page_0056.png",
      "size": {
        "width": 1029,
        "height": 1410
      }
    },
    {
      "page": 57,
      "image": "F:\\材料科学基础_知识库\\01_renders\\page_0057.png",
      "size": {
        "width": 1029,
        "height": 1410
      }
    },
    {
      "page": 58,
      "image": "F:\\材料科学基础_知识库\\01_renders\\page_0058.png",
      "size": {
        "width": 1029,
        "height": 1410
      }
    },
    {
      "page": 59,
      "image": "F:\\材料科学基础_知识库\\01_renders\\page_0059.png",
      "size": {
        "width": 1029,
        "height": 1410
      }
    },
    {
      "page": 60,
      "image": "F:\\材料科学基础_知识库\\01_renders\\page_0060.png",
      "size": {
        "width": 1029,
        "height": 1410
      }
    },
    {
      "page": 61,
      "image": "F:\\材料科学基础_知识库\\01_renders\\page_0061.png",
      "size": {
        "width": 1029,
        "height": 1410
      }
    },
    {
      "page": 62,
      "image": "F:\\材料科学基础_知识库\\01_renders\\page_0062.png",
      "size": {
        "width": 1029,
        "height": 1410
      }
    },
    {
      "page": 63,
      "image": "F:\\材料科学基础_知识库\\01_renders\\page_0063.png",
      "size": {
        "width": 1029,
        "height": 1410
      }
    },
    {
      "page": 64,
      "image": "F:\\材料科学基础_知识库\\01_renders\\page_0064.png",
      "size": {
        "width": 1029,
        "height": 1410
      }
    },
    {
      "page": 65,
      "image": "F:\\材料科学基础_知识库\\01_renders\\page_0065.png",
      "size": {
        "width": 1029,
        "height": 1410
      }
    },
    {
      "page": 66,
      "image": "F:\\材料科学基础_知识库\\01_renders\\page_0066.png",
      "size": {
        "width": 1029,
        "height": 1410
      }
    },
    {
      "page": 67,
      "image": "F:\\材料科学基础_知识库\\01_renders\\page_0067.png",
      "size": {
        "width": 1029,
        "height": 1410
      }
    },
    {
      "page": 68,
      "image": "F:\\材料科学基础_知识库\\01_renders\\page_0068.png",
      "size": {
        "width": 1029,
        "height": 1410
      }
    },
    {
      "page": 69,
      "image": "F:\\材料科学基础_知识库\\01_renders\\page_0069.png",
      "size": {
        "width": 1029,
        "height": 1410
      }
    },
    {
      "page": 70,
      "image": "F:\\材料科学基础_知识库\\01_renders\\page_0070.png",
      "size": {
        "width": 1029,
        "height": 1410
      }
    },
    {
      "page": 71,
      "image": "F:\\材料科学基础_知识库\\01_renders\\page_0071.png",
      "size": {
        "width": 1029,
        "height": 1410
      }
    },
    {
      "page": 72,
      "image": "F:\\材料科学基础_知识库\\01_renders\\page_0072.png",
      "size": {
        "width": 1029,
        "height": 1410
      }
    },
    {
      "page": 73,
      "image": "F:\\材料科学基础_知识库\\01_renders\\page_0073.png",
      "size": {
        "width": 1029,
        "height": 1410
      }
    },
    {
      "page": 74,
      "image": "F:\\材料科学基础_知识库\\01_renders\\page_0074.png",
      "size": {
        "width": 1029,
        "height": 1410
      }
    },
    {
      "page": 75,
      "image": "F:\\材料科学基础_知识库\\01_renders\\page_0075.png",
      "size": {
        "width": 1029,
        "height": 1410
      }
    },
    {
      "page": 76,
      "image": "F:\\材料科学基础_知识库\\01_renders\\page_0076.png",
      "size": {
        "width": 1029,
        "height": 1410
      }
    },
    {
      "page": 77,
      "image": "F:\\材料科学基础_知识库\\01_renders\\page_0077.png",
      "size": {
        "width": 1029,
        "height": 1410
      }
    },
    {
      "page": 78,
      "image": "F:\\材料科学基础_知识库\\01_renders\\page_0078.png",
      "size": {
        "width": 1029,
        "height": 1410
      }
    },
    {
      "page": 79,
      "image": "F:\\材料科学基础_知识库\\01_renders\\page_0079.png",
      "size": {
        "width": 1029,
        "height": 1410
      }
    },
    {
      "page": 80,
      "image": "F:\\材料科学基础_知识库\\01_renders\\page_0080.png",
      "size": {
        "width": 1029,
        "height": 1410
      }
    },
    {
      "page": 81,
      "image": "F:\\材料科学基础_知识库\\01_renders\\page_0081.png",
      "size": {
        "width": 1029,
        "height": 1410
      }
    },
    {
      "page": 82,
      "image": "F:\\材料科学基础_知识库\\01_renders\\page_0082.png",
      "size": {
        "width": 1029,
        "height": 1410
      }
    },
    {
      "page": 83,
      "image": "F:\\材料科学基础_知识库\\01_renders\\page_0083.png",
      "size": {
        "width": 1029,
        "height": 1410
      }
    },
    {
      "page": 84,
      "image": "F:\\材料科学基础_知识库\\01_renders\\page_0084.png",
      "size": {
        "width": 1029,
        "height": 1410
      }
    },
    {
      "page": 85,
      "image": "F:\\材料科学基础_知识库\\01_renders\\page_0085.png",
      "size": {
        "width": 1029,
        "height": 1410
      }
    },
    {
      "page": 86,
      "image": "F:\\材料科学基础_知识库\\01_renders\\page_0086.png",
      "size": {
        "width": 1029,
        "height": 1410
      }
    },
    {
      "page": 87,
      "image": "F:\\材料科学基础_知识库\\01_renders\\page_0087.png",
      "size": {
        "width": 1029,
        "height": 1410
      }
    },
    {
      "page": 88,
      "image": "F:\\材料科学基础_知识库\\01_renders\\page_0088.png",
      "size": {
        "width": 1029,
        "height": 1410
      }
    },
    {
      "page": 89,
      "image": "F:\\材料科学基础_知识库\\01_renders\\page_0089.png",
      "size": {
        "width": 1029,
        "height": 1410
      }
    },
    {
      "page": 90,
      "image": "F:\\材料科学基础_知识库\\01_renders\\page_0090.png",
      "size": {
        "width": 1029,
        "height": 1410
      }
    },
    {
      "page": 91,
      "image": "F:\\材料科学基础_知识库\\01_renders\\page_0091.png",
      "size": {
        "width": 1029,
        "height": 1410
      }
    },
    {
      "page": 92,
      "image": "F:\\材料科学基础_知识库\\01_renders\\page_0092.png",
      "size": {
        "width": 1029,
        "height": 1410
      }
    },
    {
      "page": 93,
      "image": "F:\\材料科学基础_知识库\\01_renders\\page_0093.png",
      "size": {
        "width": 1029,
        "height": 1410
      }
    },
    {
      "page": 94,
      "image": "F:\\材料科学基础_知识库\\01_renders\\page_0094.png",
      "size": {
        "width": 1029,
        "height": 1410
      }
    },
    {
      "page": 95,
      "image": "F:\\材料科学基础_知识库\\01_renders\\page_0095.png",
      "size": {
        "width": 1029,
        "height": 1410
      }
    },
    {
      "page": 96,
      "image": "F:\\材料科学基础_知识库\\01_renders\\page_0096.png",
      "size": {
        "width": 1029,
        "height": 1410
      }
    },
    {
      "page": 97,
      "image": "F:\\材料科学基础_知识库\\01_renders\\page_0097.png",
      "size": {
        "width": 1029,
        "height": 1410
      }
    },
    {
      "page": 98,
      "image": "F:\\材料科学基础_知识库\\01_renders\\page_0098.png",
      "size": {
        "width": 1029,
        "height": 1410
      }
    },
    {
      "page": 99,
      "image": "F:\\材料科学基础_知识库\\01_renders\\page_0099.png",
      "size": {
        "width": 1029,
        "height": 1410
      }
    },
    {
      "page": 100,
      "image": "F:\\材料科学基础_知识库\\01_renders\\page_0100.png",
      "size": {
        "width": 1029,
        "height": 1410
      }
    }
  ]
}